imandrax_tools/__init__.py
imandrax_tools/api_models.py
imandrax_tools/iml_query.py
imandrax_tools-0.1.0.dist-info/WHEEL
imandrax_tools-0.1.0.dist-info/METADATA
imandrax_tools-0.1.0.dist-info/RECORD
